unv/Unveil_banner.txt
unv/__init__.py
unv/cli.py
unv/daemon.py
unv/static_parser.py
unv-0.4.0.dist-info/METADATA
unv-0.4.0.dist-info/WHEEL
unv-0.4.0.dist-info/entry_points.txt
unv-0.4.0.dist-info/top_level.txt
unv-0.4.0.dist-info/RECORD
