Metadata-Version: 2.4
Name: unv
Version: 0.4.0
Author: Jerrod Baker
Requires-Python: >=3.9
Requires-Dist: lief
Requires-Dist: pefile
Requires-Dist: fastapi
Requires-Dist: uvicorn
Requires-Dist: python-multipart
